LICENSE
MANIFEST.in
README.rst
setup.py
inmagik_drf_auth/__init__.py
inmagik_drf_auth/admin.py
inmagik_drf_auth/models.py
inmagik_drf_auth/serializers.py
inmagik_drf_auth/tests.py
inmagik_drf_auth/views.py
inmagik_drf_auth.egg-info/PKG-INFO
inmagik_drf_auth.egg-info/SOURCES.txt
inmagik_drf_auth.egg-info/dependency_links.txt
inmagik_drf_auth.egg-info/requires.txt
inmagik_drf_auth.egg-info/top_level.txt