Metadata-Version: 1.1
Name: inmagik-drf-auth
Version: 0.1.1
Summary: Additional views and helpers for django-rest-framework authentication
Home-page: https://github.com/INMAGIK/inmagik-drf-auth/
Author: Mauro Bianchi
Author-email: bianchimro@gmail.com
License: BSD License
Platform: UNKNOWN
Classifier: Environment :: Web Environment
Classifier: Framework :: Django
Classifier: Intended Audience :: Developers
Classifier: License :: OSI Approved :: BSD License
Classifier: Operating System :: OS Independent
Classifier: Programming Language :: Python
Classifier: Programming Language :: Python :: 2
Classifier: Programming Language :: Python :: 2.7
Classifier: Topic :: Internet :: WWW/HTTP
Classifier: Topic :: Internet :: WWW/HTTP :: Dynamic Content
